LICENSE
README.md
setup.py
hashem/__init__.py
hashem/queue.py
hashem/stack.py
hashem.egg-info/PKG-INFO
hashem.egg-info/SOURCES.txt
hashem.egg-info/dependency_links.txt
hashem.egg-info/top_level.txt