Metadata-Version: 2.1
Name: hashem
Version: 0.3.0
Summary: My Codes
Home-page: https://github.com/githashem/hashem
Author: Hashem
Author-email: PersonalHashem@gmail.com
License: MIT
Platform: UNKNOWN
License-File: LICENSE
